aiotruenas_client/__init__.py
aiotruenas_client/dataset.py
aiotruenas_client/disk.py
aiotruenas_client/jail.py
aiotruenas_client/job.py
aiotruenas_client/machine.py
aiotruenas_client/pool.py
aiotruenas_client/virtualmachine.py
aiotruenas_client/websockets/__init__.py
aiotruenas_client/websockets/dataset.py
aiotruenas_client/websockets/disk.py
aiotruenas_client/websockets/interfaces.py
aiotruenas_client/websockets/jail.py
aiotruenas_client/websockets/job.py
aiotruenas_client/websockets/machine.py
aiotruenas_client/websockets/pool.py
aiotruenas_client/websockets/protocol.py
aiotruenas_client/websockets/virtualmachine.py
tests/__init__.py
tests/fakes/__init__.py
tests/fakes/fakeserver.py
aiotruenas_client-0.10.0.dist-info/LICENSE
aiotruenas_client-0.10.0.dist-info/METADATA
aiotruenas_client-0.10.0.dist-info/WHEEL
aiotruenas_client-0.10.0.dist-info/top_level.txt
aiotruenas_client-0.10.0.dist-info/RECORD
