Metadata-Version: 2.1
Name: aiotruenas-client
Version: 0.10.0
Summary: A Python client library for the TrueNAS API
Author: Shawn Wilsher
Author-email: me@shawnwilsher.com
Project-URL: Bug Reports, https://github.com/sdwilsh/aiotruenas-client/issues
Project-URL: Release Notes, https://github.com/sdwilsh/aiotruenas-client/releases/
Project-URL: Source, https://github.com/sdwilsh/aiotruenas-client
Classifier: Development Status :: 3 - Alpha
Classifier: License :: OSI Approved :: MIT License
Classifier: Operating System :: OS Independent
Classifier: Programming Language :: Python :: 3.8
Classifier: Programming Language :: Python :: 3.9
Classifier: Programming Language :: Python :: 3.10
Classifier: Programming Language :: Python :: 3.11
Requires-Python: <4,>3.8
License-File: LICENSE
Requires-Dist: websockets (==11.0.1)
Requires-Dist: meteor-ejson (==1.1.0)
